Workbook

Sheet MASTER
A1: ISBN | B1: TITLE | C1: GRADE | D1: SUBJECT | E1: LANGUAGE | F1: PRICE | G1: PUBLISHER
A2: 9781920192228 | B2: Understanding Life Sciences Grade 10 – Learner’s Book (3rd edition - CAPS) | F2: 0 | G2: Pulse
A3: 9781920192235 | B3: Understanding Life Sciences Grade 10 – Teacher’s Guide (3rd edition - CAPS) | F3: 0 | G3: Pulse
A4: 9781920192266 | B4: Understanding Life Sciences Grade 11 – Learner’s Book (3rd edition - CAPS) | F4: 0 | G4: Pulse
A5: 9781920192273 | B5: Understanding Life Sciences Grade 11 – Teacher’s Guide (3rd edition - CAPS) | F5: 0 | G5: Pulse
A6: 9781920192280 | B6: Understanding Life Sciences Grade 12 – Learner’s Book (3rd edition - CAPS) | F6: 0 | G6: Pulse
A7: 9781920192297 | B7: Understanding Life Sciences Grade 12 – Teacher’s Guide (3rd edition - CAPS) | F7: 0 | G7: Pulse
A8: 9781920192242 | B8: Study Guide for Understanding Life Sciences including Questions and Answers - Grade 10 CAPS (3rd edition) | F8: 0 | G8: Pulse
A9: 9781920192327 | B9: Study Guide for Understanding Life Sciences - Grade 11 CAPS (3rd edition) | F9: 0 | G9: Pulse
A10: 9781920192303 | B10: Study Guide for Understanding Life Sciences including Questions and Answers - Grade 12 CAPS (3rd edition) | F10: 0 | G10: Pulse
A11: 9781920192310 | B11: Studiegids vir Verstaan Lewenswetenskappe insluitende Vrae & Antwoorde - Graad 12 | F11: 0 | G11: Pulse
A12: 9781920192259 | B12: Workbook for Understanding Life Sciences - Grade 12 CAPS | F12: 0 | G12: Pulse
A13: 9781920192990 | B13: Werkboek vir Verstaan Lewenswetenskappe - Graad 12 CAPS | F13: 0 | G13: Pulse
A14: 9780190402549 | B14: Oxford Kereiti ya R Buka ya puiso 1: Nna | C14: R | D14: Language | E14: Setswana | F14: 32.95 | G14: OXFORD
A15: 9780190408527 | B15: Oxford Kereiti ya R Buka ya puiso 2: Kwa sekolong | C15: R | D15: Language | E15: Setswana | F15: 32.95 | G15: OXFORD
A16: 9780190407179 | B16: Oxford Kereiti ya R Buka ya puiso 3: Phaposiborutelo | C16: R | D16: Language | E16: Setswana | F16: 32.95 | G16: OXFORD
A17: 9780190403447 | B17: Oxford Kereiti ya R Buka ya puiso 4: Dibuka | C17: R | D17: Language | E17: Setswana | F17: 32.95 | G17: OXFORD
A18: 9780199046935 | B18: Oxford Kereiti ya R Buka ya puiso 5: Malatsi a beke | C18: R | D18: Language | E18: Setswana | F18: 32.95 | G18: OXFORD
A19: 9780190403850 | B19: Oxford Kereiti ya R Buka ya puiso 6: Mmele wa me | C19: R | D19: Language | E19: Setswana | F19: 32.95 | G19: OXFORD
A20: 9780190402471 | B20: Oxford Kereiti ya R Buka ya puiso 7: Botshelo jo bo itekanetseng | C20: R | D20: Language | E20: Setswana | F20: 32.95 | G20: OXFORD
A21: 9780190403928 | B21: Oxford Kereiti ya R Buka ya puiso 8: Selemo | C21: R | D21: Language | E21: Setswana | F21: 32.95 | G21: OXFORD
A22: 9780199075133 | B22: Oxford Kereiti ya R Buka ya puiso 9: Dipopego le mebala | C22: R | D22: Language | E22: Setswana | F22: 32.95 | G22: OXFORD
A23: 9780190408480 | B23: Oxford Kereiti ya R Buka ya puiso 10: Leeto le le monate | C23: R | D23: Language | E23: Setswana | F23: 32.95 | G23: OXFORD
A24: 9780190405182 | B24: Oxford Kereiti ya R Buka ya puiso 11: Legae | C24: R | D24: Language | E24: Setswana | F24: 32.95 | G24: OXFORD
A25: 9780190400996 | B25: Oxford Kereiti ya R Buka ya puiso 12: Tshireletsego | C25: R | D25: Language | E25: Setswana | F25: 32.95 | G25: OXFORD
... A409: 9780195989618 | B409: We are growing Grade R Teacherʼs Book | C409: R | D409: Language | E409: English | F409: 505.95 | G409: OXFORD
A410: 9780195980240 | B410: We are growing Stage 1 Readers (Pack of 12) | D410: Language | E410: English | F410: 801.95 | G410: OXFORD
A411: 9780195980271 | B411: Big and Small | C411: 1 | D411: Language | E411: English | F411: 43.95 | G411: OXFORD
A412: 9780195980288 | B412: Play with me | C412: 1 | D412: Language | E412: English | F412: 43.95 | G412: OXFORD
A413: 9780195980295 | B413: Hands talk | C413: 1 | D413: Language | E413: English | F413: 43.95 | G413: OXFORD
A414: 9780195980301 | B414: The red ball | C414: 1 | D414: Language | E414: English | F414: 43.95 | G414: OXFORD
A415: 9780195980318 | B415: Look and listen | C415: 1 | D415: Language | E415: English | F415: 43.95 | G415: OXFORD
A416: 9780195980325 | B416: Count with me | C416: 1 | D416: Language | E416: English | F416: 43.95 | G416: OXFORD
A417: 9780195980332 | B417: Days | C417: 1 | D417: Language | E417: English | F417: 43.95 | G417: OXFORD
A418: 9780195980349 | B418: Fire | C418: 1 | D418: Language | E418: English | F418: 43.95 | G418: OXFORD
A419: 9780195980356 | B419: Food of many colours | C419: 1 | D419: Language | E419: English | F419: 43.95 | G419: OXFORD
A420: 9780195980363 | B420: Sleepy boy | C420: 1 | D420: Language | E420: English | F420: 43.95 | G420: OXFORD
A421: 9780195980370 | B421: Run, cat boy, run | C421: 1 | D421: Language | E421: English | F421: 43.95 | G421: OXFORD
A422: 9780195980387 | B422: My dreams | C422: 1 | D422: Language | E422: English | F422: 43.95 | G422: OXFORD
A423: 9780195988758 | B423: We are growing Stage 1 Big Book Big and Small The red ball Run, cat boy, run My dreams | D423: Language | E423: English | F423: 717.95 | G423: OXFORD
A424: 9780199051281 | B424: We are growing Stage 1 Teacherʼs Notes | C424: 1 | D424: Language | E424: English | F424: 68.95 | G424: OXFORD
A425: 9780195980257 | B425: We are growing Stage 2 Readers (Pack of 8) | D425: Language | E425: English | F425: 658.95 | G425: OXFORD
A426: 9780195980394 | B426: The farm song | C426: 2 | D426: Language | E426: English | F426: 51.95 | G426: OXFORD
A427: 9780195980400 | B427: Rosy and the mice | C427: 2 | D427: Language | E427: English | F427: 51.95 | G427: OXFORD
A428: 9780195980417 | B428: The best for me | C428: 2 | D428: Language | E428: English | F428: 51.95 | G428: OXFORD
A429: 9780195980424 | B429: The bad storm | C429: 2 | D429: Language | E429: English | F429: 51.95 | G429: OXFORD
A430: 9780195980431 | B430: Crocodile, Tortoise and the kind man | C430: 2 | D430: Language | E430: English | F430: 51.95 | G430: OXFORD
A431: 9780195980448 | B431: My birthday present | C431: 2 | D431: Language | E431: English | F431: 51.95 | G431: OXFORD
A432: 9780195980455 | B432: The circus comes to town | C432: 2 | D432: Language | E432: English | F432: 51.95 | G432: OXFORD
A433: 9780195980462 | B433: The big bully | C433: 2 | D433: Language | E433: English | F433: 51.95 | G433: OXFORD
A434: 9780195988765 | B434: We are growing Stage 2 Big Book The best for me The big bully | D434: Language | E434: English | F434: 717.95 | G434: OXFORD
A435: 9780199053223 | B435: We are growing Stage 2 Teacherʼs Notes | C435: 2 | D435: Language | E435: English | F435: 68.95 | G435: OXFORD
A436: 9780195980264 | B436: We are growing Stage 3 Readers (Pack of 4) | D436: Language | E436: English | F436: 528.95 | G436: OXFORD
A437: 9780195980479 | B437: A scary story | C437: 3 | D437: Language | E437: English | F437: 82.95 | G437: OXFORD
A438: 9780195980486 | B438: The TV star | C438: 3 | D438: Language | E438: English | F438: 82.95 | G438: OXFORD
A439: 9780195980493 | B439: Bettyʼs braids | C439: 3 | D439: Language | E439: English | F439: 82.95 | G439: OXFORD
A440: 9780195980509 | B440: Our forest adventure | C440: 3 | D440: Language | E440: English | F440: 82.95 | G440: OXFORD
A441: 9780195992465 | B441: Dusty and Daisy | C441: 3 | D441: Language | E441: English | F441: 82.95 | G441: OXFORD
A442: 9780195992472 | B442: Montyʼs Terrible Itch | C442: 3 | D442: Language | E442: English | F442: 82.95 | G442: OXFORD
A443: 9780199049271 | B443: We are growing Stage 3 Teacherʼs Notes | C443: 3 | D443: Language | E443: English | F443: 68.95 | G443: OXFORD
A444: 9780195988000 | B444: We are growing Stage 1–3 Anthology The red ball (Stage 1) Run, cat boy, run (Stage 1) My dreams (Stage 1) The big bully (Stage 2) The TV star (Stage 3) Bettyʼs braids (Stage 3) Our forest adventure (Stage 3) | C444: 1 - 3 | D444: Language | E444: English | F444: 277.95 | G444: OXFORD
A445: 9780195982190 | B445: We are growing Stage 1–3 Teacherʼs Notes (Pack) | D445: Language | E445: English | F445: 411.95 | G445: OXFORD
A446: 9780195982503 | B446: We are growing Stage 4 Readers (Pack of 4) | D446: Language | E446: English | F446: 591.95 | G446: OXFORD
A447: 9780195982381 | B447: The promise of sunshine | D447: Language | E447: English | F447: 79.95 | G447: OXFORD
A448: 9780195982398 | B448: A ponyʼs tale | D448: Language | E448: English | F448: 79.95 | G448: OXFORD
A449: 9780195982404 | B449: Never give up | D449: Language | E449: English | F449: 79.95 | G449: OXFORD
A450: 9780195982411 | B450: The brave and the beautiful | D450: Language | E450: English | F450: 79.95 | G450: OXFORD
A451: 9780195982534 | B451: We are growing Stage 4 Teacherʼs Notes | D451: Language | E451: English | F451: 144.95 | G451: OXFORD
A452: 9780195982510 | B452: We are growing Stage 5 Readers (Pack of 4) | D452: Language | E452: English | F452: 780.95 | G452: OXFORD
A453: 9780195982428 | B453: Youʼd do the same for me | D453: Language | E453: English | F453: 92.95 | G453: OXFORD
A454: 9780195982435 | B454: The message in the dream | D454: Language | E454: English | F454: 92.95 | G454: OXFORD
A455: 9780195982442 | B455: The hyena, the hare & the stork | D455: Language | E455: English | F455: 92.95 | G455: OXFORD
A456: 9780195982459 | B456: Paragon the perfect pig | D456: Language | E456: English | F456: 92.95 | G456: OXFORD
... A515: 9780195985580 | B515: Die riviertroue | D515: Language | E515: Afrikaans | F515: 105.95 | G515: OXFORD
A516: 9780797809529 | B516: Kom Ons Lees Wit Vlak: Boeke een tot nege | C516: 1 | D516: Language | E516: Afrikaans | F516: 676.95 | G516: OXFORD
A517: 9780333403136 | B517: Kom Ons Lees Pienk Vlak: Ben se boek | C517: 1 | D517: Language | E517: Afrikaans | F517: 136.95 | G517: OXFORD
A518: 9780333589625 | B518: Kom Ons Lees Pienk Vlak: By die pretpark | C518: 1 | D518: Language | E518: Afrikaans | F518: 136.95 | G518: OXFORD
A519: 9780333584293 | B519: Kom Ons Lees Pienk Vlak: Die maats | C519: 1 | D519: Language | E519: Afrikaans | F519: 74.95 | G519: OXFORD
A520: 9780333559970 | B520: Kom Ons Lees Pienk Vlak: Jaap se boek | C520: 1 | D520: Language | E520: Afrikaans | F520: 74.95 | G520: OXFORD
A521: 9780333559963 | B521: Kom Ons Lees Pienk Vlak: Kiep se boek | C521: 1 | D521: Language | E521: Afrikaans | F521: 74.95 | G521: OXFORD
A522: 9780333589632 | B522: Kom Ons Lees Pienk Vlak: Leeu is siek | C522: 1 | D522: Language | E522: Afrikaans | F522: 136.95 | G522: OXFORD
A523: 9780333584309 | B523: Kom Ons Lees Pienk Vlak: Riet se boek | C523: 1 | D523: Language | E523: Afrikaans | F523: 74.95 | G523: OXFORD
A524: 9780333559901 | B524: Kom Ons Lees Pienk Vlak: Tom se boek | C524: 1 | D524: Language | E524: Afrikaans | F524: 74.95 | G524: OXFORD
A525: 9780333589618 | B525: Kom Ons Lees Pienk Vlak: Vet vark se boek | C525: 1 | D525: Language | E525: Afrikaans | F525: 136.95 | G525: OXFORD
A526: 9780333589663 | B526: Kom Ons Lees Rooi Vlak: Ben se been en By die tandarts | C526: 1 | D526: Language | E526: Afrikaans | F526: 74.95 | G526: OXFORD
A527: 9780333589724 | B527: Kom Ons Lees Rooi Vlak: Hans se fiets en Is dit jou hoed? | C527: 1 | D527: Language | E527: Afrikaans | F527: 74.95 | G527: OXFORD
... A1087: 9780195998269 | B1087: Oxford Umkhanyo Grade 3 Teacher's Guide (IsiNdebele) Oxford Umkhanyo IGreyidi 3 UMhlahlandlela kaTitjhere | C1087: 3 | D1087: Language | E1087: IsiNdebele | F1087: 285.95 | G1087: OXFORD
A1088: 9780195769166 | B1088: Siyakhula IsiNdebele Stage 1 Readers (Pack of 12) | D1088: Literacy | E1088: IsiNdebele | F1088: 801.95 | G1088: OXFORD
A1089: 9780195769753 | B1089: Ukweqiwa kwendlela | C1089: 1 | D1089: Language | E1089: IsiNdebele | F1089: 48.95 | G1089: OXFORD
A1090: 9780195769760 | B1090: Iminwakho ithini? | C1090: 1 | D1090: Language | E1090: IsiNdebele | F1090: 48.95 | G1090: OXFORD
A1091: 9780195769777 | B1091: Abonodoli bami | C1091: 1 | D1091: Language | E1091: IsiNdebele | F1091: 48.95 | G1091: OXFORD
A1092: 9780195769784 | B1092: Isivuno esihle | C1092: 1 | D1092: Language | E1092: IsiNdebele | F1092: 48.95 | G1092: OXFORD
A1093: 9780195769791 | B1093: Umntwana nami | C1093: 1 | D1093: Language | E1093: IsiNdebele | F1093: 48.95 | G1093: OXFORD
A1094: 9780195769807 | B1094: Ibholo ebovu | C1094: 1 | D1094: Language | E1094: IsiNdebele | F1094: 48.95 | G1094: OXFORD
A1095: 9780195769814 | B1095: Kusile | C1095: 1 | D1095: Language | E1095: IsiNdebele | F1095: 48.95 | G1095: OXFORD
A1096: 9780195769821 | B1096: Amalanga weveke | C1096: 1 | D1096: Language | E1096: IsiNdebele | F1096: 48.95 | G1096: OXFORD
A1097: 9780195769838 | B1097: Ngiyakwazi ukubala | C1097: 1 | D1097: Language | E1097: IsiNdebele | F1097: 48.95 | G1097: OXFORD
A1098: 9780195769845 | B1098: Umlilo | C1098: 1 | D1098: Language | E1098: IsiNdebele | F1098: 48.95 | G1098: OXFORD
A1099: 9780195769852 | B1099: Nangathana bengineempiko | C1099: 1 | D1099: Language | E1099: IsiNdebele | F1099: 48.95 | G1099: OXFORD
A1100: 9780195769869 | B1100: Ilanga elikhulu likaSizwe | C1100: 1 | D1100: Language | E1100: IsiNdebele | F1100: 48.95 | G1100: OXFORD
...

Sheet QUOTATION
A1: KALIKENG TRADING AND PROJECTS CC
A2: Reg No: 2010/007041/23 | VAT No: 4340257320 | Tel: 073 223 9762 | kalikengtrading@gmail.com
A3: B-BBEE LEVEL 1 | 100% BLACK OWNED | 135% PROCUREMENT RECOGNITION
A6: QUOTATION NO: | E6: DATE:
A7: SCHOOL / CLIENT: | E7: PREPARED BY:
A8: ADDRESS: | E8: PHONE:
A10: ISBN | B10: TITLE | C10: GR | D10: SUBJECT | E10: LANGUAGE | F10: PUBLISHER | G10: UNIT PRICE | H10: QTY | I10: LINE TOTAL
B11: =IFERROR(VLOOKUP(A11,MASTER!$A:$G,2,0),"") | C11: =IFERROR(VLOOKUP(A11,MASTER!$A:$G,3,0),"") | D11: =IFERROR(VLOOKUP(A11,MASTER!$A:$G,4,0),"") | E11: =IFERROR(VLOOKUP(A11,MASTER!$A:$G,5,0),"") | F11: =IFERROR(VLOOKUP(A11,MASTER!$A:$G,7,0),"") | G11: =IFERROR(VLOOKUP(A11,MASTER!$A:$G,6,0),"") | I11: =IFERROR(IF(H11="","",G11*H11),"")
B12: =IFERROR(VLOOKUP(A12,MASTER!$A:$G,2,0),"") | C12: =IFERROR(VLOOKUP(A12,MASTER!$A:$G,3,0),"") | D12: =IFERROR(VLOOKUP(A12,MASTER!$A:$G,4,0),"") | E12: =IFERROR(VLOOKUP(A12,MASTER!$A:$G,5,0),"") | F12: =IFERROR(VLOOKUP(A12,MASTER!$A:$G,7,0),"") | G12: =IFERROR(VLOOKUP(A12,MASTER!$A:$G,6,0),"") | I12: =IFERROR(IF(H12="","",G12*H12),"")
B13: =IFERROR(VLOOKUP(A13,MASTER!$A:$G,2,0),"") | C13: =IFERROR(VLOOKUP(A13,MASTER!$A:$G,3,0),"") | D13: =IFERROR(VLOOKUP(A13,MASTER!$A:$G,4,0),"") | E13: =IFERROR(VLOOKUP(A13,MASTER!$A:$G,5,0),"") | F13: =IFERROR(VLOOKUP(A13,MASTER!$A:$G,7,0),"") | G13: =IFERROR(VLOOKUP(A13,MASTER!$A:$G,6,0),"") | I13: =IFERROR(IF(H13="","",G13*H13),"")
B14: =IFERROR(VLOOKUP(A14,MASTER!$A:$G,2,0),"") | C14: =IFERROR(VLOOKUP(A14,MASTER!$A:$G,3,0),"") | D14: =IFERROR(VLOOKUP(A14,MASTER!$A:$G,4,0),"") | E14: =IFERROR(VLOOKUP(A14,MASTER!$A:$G,5,0),"") | F14: =IFERROR(VLOOKUP(A14,MASTER!$A:$G,7,0),"") | G14: =IFERROR(VLOOKUP(A14,MASTER!$A:$G,6,0),"") | I14: =IFERROR(IF(H14="","",G14*H14),"")
B15: =IFERROR(VLOOKUP(A15,MASTER!$A:$G,2,0),"") | C15: =IFERROR(VLOOKUP(A15,MASTER!$A:$G,3,0),"") | D15: =IFERROR(VLOOKUP(A15,MASTER!$A:$G,4,0),"") | E15: =IFERROR(VLOOKUP(A15,MASTER!$A:$G,5,0),"") | F15: =IFERROR(VLOOKUP(A15,MASTER!$A:$G,7,0),"") | G15: =IFERROR(VLOOKUP(A15,MASTER!$A:$G,6,0),"") | I15: =IFERROR(IF(H15="","",G15*H15),"")
B16: =IFERROR(VLOOKUP(A16,MASTER!$A:$G,2,0),"") | C16: =IFERROR(VLOOKUP(A16,MASTER!$A:$G,3,0),"") | D16: =IFERROR(VLOOKUP(A16,MASTER!$A:$G,4,0),"") | E16: =IFERROR(VLOOKUP(A16,MASTER!$A:$G,5,0),"") | F16: =IFERROR(VLOOKUP(A16,MASTER!$A:$G,7,0),"") | G16: =IFERROR(VLOOKUP(A16,MASTER!$A:$G,6,0),"") | I16: =IFERROR(IF(H16="","",G16*H16),"")
B17: =IFERROR(VLOOKUP(A17,MASTER!$A:$G,2,0),"") | C17: =IFERROR(VLOOKUP(A17,MASTER!$A:$G,3,0),"") | D17: =IFERROR(VLOOKUP(A17,MASTER!$A:$G,4,0),"") | E17: =IFERROR(VLOOKUP(A17,MASTER!$A:$G,5,0),"") | F17: =IFERROR(VLOOKUP(A17,MASTER!$A:$G,7,0),"") | G17: =IFERROR(VLOOKUP(A17,MASTER!$A:$G,6,0),"") | I17: =IFERROR(IF(H17="","",G17*H17),"")
B18: =IFERROR(VLOOKUP(A18,MASTER!$A:$G,2,0),"") | C18: =IFERROR(VLOOKUP(A18,MASTER!$A:$G,3,0),"") | D18: =IFERROR(VLOOKUP(A18,MASTER!$A:$G,4,0),"") | E18: =IFERROR(VLOOKUP(A18,MASTER!$A:$G,5,0),"") | F18: =IFERROR(VLOOKUP(A18,MASTER!$A:$G,7,0),"") | G18: =IFERROR(VLOOKUP(A18,MASTER!$A:$G,6,0),"") | I18: =IFERROR(IF(H18="","",G18*H18),"")
B19: =IFERROR(VLOOKUP(A19,MASTER!$A:$G,2,0),"") | C19: =IFERROR(VLOOKUP(A19,MASTER!$A:$G,3,0),"") | D19: =IFERROR(VLOOKUP(A19,MASTER!$A:$G,4,0),"") | E19: =IFERROR(VLOOKUP(A19,MASTER!$A:$G,5,0),"") | F19: =IFERROR(VLOOKUP(A19,MASTER!$A:$G,7,0),"") | G19: =IFERROR(VLOOKUP(A19,MASTER!$A:$G,6,0),"") | I19: =IFERROR(IF(H19="","",G19*H19),"")
B20: =IFERROR(VLOOKUP(A20,MASTER!$A:$G,2,0),"") | C20: =IFERROR(VLOOKUP(A20,MASTER!$A:$G,3,0),"") | D20: =IFERROR(VLOOKUP(A20,MASTER!$A:$G,4,0),"") | E20: =IFERROR(VLOOKUP(A20,MASTER!$A:$G,5,0),"") | F20: =IFERROR(VLOOKUP(A20,MASTER!$A:$G,7,0),"") | G20: =IFERROR(VLOOKUP(A20,MASTER!$A:$G,6,0),"") | I20: =IFERROR(IF(H20="","",G20*H20),"")
B21: =IFERROR(VLOOKUP(A21,MASTER!$A:$G,2,0),"") | C21: =IFERROR(VLOOKUP(A21,MASTER!$A:$G,3,0),"") | D21: =IFERROR(VLOOKUP(A21,MASTER!$A:$G,4,0),"") | E21: =IFERROR(VLOOKUP(A21,MASTER!$A:$G,5,0),"") | F21: =IFERROR(VLOOKUP(A21,MASTER!$A:$G,7,0),"") | G21: =IFERROR(VLOOKUP(A21,MASTER!$A:$G,6,0),"") | I21: =IFERROR(IF(H21="","",G21*H21),"")
B22: =IFERROR(VLOOKUP(A22,MASTER!$A:$G,2,0),"") | C22: =IFERROR(VLOOKUP(A22,MASTER!$A:$G,3,0),"") | D22: =IFERROR(VLOOKUP(A22,MASTER!$A:$G,4,0),"") | E22: =IFERROR(VLOOKUP(A22,MASTER!$A:$G,5,0),"") | F22: =IFERROR(VLOOKUP(A22,MASTER!$A:$G,7,0),"") | G22: =IFERROR(VLOOKUP(A22,MASTER!$A:$G,6,0),"") | I22: =IFERROR(IF(H22="","",G22*H22),"")
... B210: =IFERROR(VLOOKUP(A210,MASTER!$A:$G,2,0),"") | C210: =IFERROR(VLOOKUP(A210,MASTER!$A:$G,3,0),"") | D210: =IFERROR(VLOOKUP(A210,MASTER!$A:$G,4,0),"") | E210: =IFERROR(VLOOKUP(A210,MASTER!$A:$G,5,0),"") | F210: =IFERROR(VLOOKUP(A210,MASTER!$A:$G,7,0),"") | G210: =IFERROR(VLOOKUP(A210,MASTER!$A:$G,6,0),"") | I210: =IFERROR(IF(H210="","",G210*H210),"")
A211: GRAND TOTAL | I211: =IFERROR(SUM(I11:I210),0)
